apiutils/__init__.py
apiutils/calculator.py
apiutils/chart.py
apiutils/dataset.py
apiutils/entity.py
apiutils/llm_service.py
apiutils/sentence_encoder.py
apiutils/dataset/APIBENCH/Q_test.csv
apiutils/dataset/APIBENCH/Q_train.csv
apiutils/dataset/BIKER/BIKER_test.csv
apiutils/dataset/BIKER/BIKER_test_filtered.csv
apiutils/dataset/BIKER/BIKER_train.csv
apiutils/dataset/doc/doc_APIs_descriptions.csv
apiutils_rec-0.1.1.dist-info/licenses/LICENSE
apiutils_rec-0.1.1.dist-info/METADATA
apiutils_rec-0.1.1.dist-info/WHEEL
apiutils_rec-0.1.1.dist-info/top_level.txt
apiutils_rec-0.1.1.dist-info/RECORD
