Metadata-Version: 2.4
Name: apiutils-rec
Version: 0.1.1
Summary: API Recommended Field Research Toolkit
Author-email: WhiteRain2 <liyumail2024@gmail.com>
License: MIT
Project-URL: Homepage, https://github.com/WhiteRain2/APIUtils
Project-URL: Bug Tracker, https://github.com/WhiteRain2/APIUtils/issues
Classifier: License :: OSI Approved :: MIT License
Classifier: Programming Language :: Python :: 3
Classifier: Programming Language :: Python :: 3.8
Classifier: Programming Language :: Python :: 3.9
Classifier: Programming Language :: Python :: 3.10
Classifier: Programming Language :: Python :: 3.11
Classifier: Programming Language :: Python :: 3.12
Classifier: Topic :: Scientific/Engineering :: Artificial Intelligence
Classifier: Development Status :: 4 - Beta
Requires-Python: >=3.10
License-File: LICENSE
Requires-Dist: matplotlib>=3.10.3
Requires-Dist: nltk>=3.9.1
Requires-Dist: openai>=1.75.0
Requires-Dist: pandas>=2.2.3
Requires-Dist: scikit-learn>=1.6.1
Requires-Dist: sentence-transformers>=4.1.0
Requires-Dist: tqdm>=4.67.1
Dynamic: license-file
